afreeca/__init__.py
afreeca/constants.py
afreeca/core.py
afreeca/credential.py
afreeca/exceptions.py
afreeca/interfaces.py
afreeca/packet.py
afreeca/utils.py
afreeca/types/bj_info.py
afreeca/types/packet.py
afreeca-0.5.8.dist-info/licenses/LICENSE
afreeca-0.5.8.dist-info/METADATA
afreeca-0.5.8.dist-info/WHEEL
afreeca-0.5.8.dist-info/top_level.txt
afreeca-0.5.8.dist-info/RECORD
