Metadata-Version: 2.4
Name: afreeca
Version: 0.5.8
Summary: AfreecaTV API Wrapper
Author-email: minibox <minibox724@gmail.com>
License: MIT
Project-URL: homepage, https://github.com/wakscord/afreeca
Project-URL: repository, https://github.com/wakscord/afreeca
Requires-Python: >=3.9
License-File: LICENSE
Requires-Dist: aiohttp
Requires-Dist: orjson
Requires-Dist: typing_extensions
Dynamic: license-file
